{
  "version": "1.0",
  "lastUpdated": "2024-01-30",
  "description": "Hebrew call classifications for customer service calls",
  "classifications": [
    "שיקוף עסקה",
    "הסבר חשבונית או חיוב",
    "בירור פרטי תכנית/ מסלול",
    "מעבר תכנית/ מסלול",
    "בירור חוב",
    "תשלום חוב",
    "תשלום חשבונית עתידית/יתרות ציוד",
    "עדכון אמצעי תשלום",
    "שליחת העתקי חשבונית",
    "שירות תיקונים – עלויות",
    "שירות תיקונים -הצטרפות",
    "שירות תיקונים -ביטול",
    "שירות סייבר",
    "שירות בקרת הורים",
    "מידע על חבילת חו״ל",
    "רכישת חבילת חו״ל ראשי",
    "רכישת חבילת חול בן משפחה",
    "ביטול/שינוי חבילת חו״ל",
    "בירור מצב חשבון",
    "חבילת חו״ל -בירור מצב חשבון /תוקף חבילה",
    "שירות סינון שיחות – הצטרפות",
    "שירות סינון שיחות -ביטול",
    "שירות סינון שיחות -תפעול תקלה",
    "רכישת גלובל סים/ESIM",
    "בירור יתרה גלובל סים/ESIM",
    "טעינת גלובל סים/ESIM",
    "ESIM בארץ – הצטרפות ותפעול",
    "שעון ESIM – עלויות",
    "שעון ESIM -הצטרפות",
    "שעון ESIM -תפעול",
    "תקלת קליטה",
    "תקלת גלישה בארץ",
    "תקלת גלישה בחול",
    "תקלת שיחות יוצאות /נכנסות בארץ",
    "תקלת שיחות יוצאות /נכנסות בחול",
    "תקלת הודעות יוצאות /נכנסות בארץ",
    "תקלת הודעות יוצאות /נכנסות בחול",
    "החלפת סים",
    "קופוני הטבה",
    "זימון תור למרכזי שירות",
    "שדרוג מכשיר חשכ״ל",
    "סיום התקשרות - ניתוק קבוע",
    "ניוד - איתות נטישה",
    "הפסקת שירות (הקפאת קו)",
    "הפסקת שירות אובדן/גניבה (ניתוק אובדן)",
    "חיבור מניתוק קבוע",
    "חיבור מניתוק אובדן",
    "חיבור מהקפאת קו",
    "העברת בעלות",
    "הוספת/הסרת שם",
    "רכישת מכשיר",
    "רכישת קו חדש",
    "ניוד קו",
    "תקלות ניוד",
    "החלפת מספר",
    "פתיחה / סגירה למידע שיווקי",
    "בקשה לפירוט שיחות",
    "ביצוע הפניית שיחות",
    "ביטול הפניית שיחות",
    "הוספת שלוחה",
    "ביטול שלוחה",
    "שליחויות – תיאום",
    "שליחויות – שינוי",
    "שליחויות – ביטול",
    "עדכון פרטים אישיים -כתובת /שם"
  ],
  "churn_detection": {
    "enabled": true,
    "threshold": 70,
    "description": "לקוח מאיים לעזוב את החברה או לעבור למתחרה כמו גולן הוט סלקום או פרטנר. לקוח לא מרוצה מהמחיר או מהשירות ומשווה הצעות מתחרים. לקוח מתלונן על חיוב גבוה מדי או ששילם יותר מהנדרש. לקוח מתוסכל מחוסר מענה או המתנה ארוכה. לקוח אומר שיקר מדי או שהוא מוטרד מהעלויות. לקוח שוקל לעזוב כי קיבל הצעה טובה יותר ממתחרה. לקוח רוצה לסגור חשבון לנתק או לנייד לחברה אחרת. לקוח מתלונן על אין שירות או בעיות קליטה חוזרות. לקוח לא מצליח לחייג או לא מקבל שיחות באופן קבוע. לקוח מתוסכל מתקלות רשת או ניתוקים חוזרים.",
    "churn_prototypes": [
      "לקוח רוצה לעבור להתנייד לעזוב לחברה אחרת כמו גולן סלקום הוט או פרטנר ניוד איתות נטישה",
      "לקוח שאין לו שימוש בקו לא צריך יותר את הקו לא מעוניין בקו מבקש לנתק אותו קבוע לבטל סיום התקשרות ניתוק קבוע",
      "לקוח חויב יותר מדי ומאיים לעזוב את פלאפון בגלל המחיר הגבוה אם לא יקבל הנחה הוא עוזב לחברה אחרת לא מוכן לשלם יותר",
      "לקוח רוצה לעזוב את פלאפון בגלל בעיה שלא נפתרה מאיים לעבור למתחרה כי לא מטפלים בו אומר שנמאס לו ועוזב",
      "לקוח קיבל הצעה זולה יותר מגולן סלקום הוט או פרטנר ושוקל לעזוב את פלאפון כי המחיר אצל המתחרה יותר טוב"
    ]
  }
}